<?xml version='1.0' encoding='UTF-8'?>
<block id="14160203629" level="17"><road id="91" name="外环"><triangles material="road" type="strip"><node x="863.663641647" y="0" z="-59.3151843585" /><node x="429.582041457" y="0" z="59.3151843362" /><node x="894.441207767" y="0" z="53.3027054369" /><node x="461.409140259" y="0" z="175.773408882" /><node x="999.397782326" y="0" z="412.253196232" /><node x="567.582565695" y="0" z="538.885518081" /><node x="1027.23970634" y="0" z="506.917056594" /><node x="603.078641683" y="0" z="659.573857721" /><node x="1073.27067584" y="0" z="614.322712634" /><node x="658.38967219" y="0" z="788.633001681" /><node x="1134.08803219" y="0" z="762.020198956" /><node x="715.806315839" y="0" z="928.071715362" /><node x="1189.3869954" y="0" z="906.649961408" /><node x="770.293352634" y="0" z="1070.57795291" /><node x="1263.0293934" y="0" z="1090.75498753" /><node x="848.664954633" y="0" z="1266.50592678" /><node x="1335.38943817" y="0" z="1252.01521532" /><node x="924.094909862" y="0" z="1434.607699" /><node x="1414.19848718" y="0" z="1431.45602904" /><node x="1002.24586086" y="0" z="1612.55008528" /><node x="1476.48004794" y="0" z="1573.00305694" /><node x="1071.34230009" y="0" z="1769.58525738" /><node x="1557.93760583" y="0" z="1726.08847655" /><node x="1163.0607422" y="0" z="1941.95423777" /><node x="1652.914819" y="0" z="1895.26545088" /><node x="1259.17752904" y="0" z="2113.16106344" /><node x="1732.07980786" y="0" z="2040.40152567" /><node x="1341.24654017" y="0" z="2263.62118865" /><node x="1798.19762652" y="0" z="2151.07690425" /><node x="1412.47672151" y="0" z="2382.85421007" /><node x="1881.03178385" y="0" z="2288.12985614" /><node x="1493.86256418" y="0" z="2517.51085818" /><node x="1984.56838663" y="0" z="2466.44391098" /><node x="1605.30396141" y="0" z="2709.43880334" /><node x="2128.23611365" y="0" z="2670.45216035" /><node x="1760.21823438" y="0" z="2929.41715397" /><node x="2309.37332019" y="0" z="2928.06942337" /><node x="1941.25589412" y="0" z="3186.89283941" /></triangles></road></block>