<?xml version='1.0' encoding='UTF-8'?>
<block id="14160205994" level="17"><road id="179" name="大学城南三路"><triangles material="road" type="strip"><node x="705.748046502" y="0" z="3060.87485035" /><node x="885.620030656" y="0" z="3054.08741248" /><node x="701.265721336" y="0" z="2942.09300214" /><node x="881.105312631" y="0" z="2934.44715188" /><node x="689.938575536" y="0" z="2702.59734941" /><node x="869.818458408" y="0" z="2695.80340461" /><node x="681.861575544" y="0" z="2416.68274941" /><node x="861.741458416" y="0" z="2409.88880461" /><node x="670.567315742" y="0" z="2177.88242212" /><node x="850.421718225" y="0" z="2170.54973191" /><node x="662.458859012" y="0" z="1941.12482191" /><node x="842.376174942" y="0" z="1935.62913211" /><node x="655.989869609" y="0" z="1700.14200022" /><node x="835.923164353" y="0" z="1695.2415538" /><node x="647.935329422" y="0" z="1408.57921378" /><node x="827.823704526" y="0" z="1402.05274024" /><node x="641.576955557" y="0" z="1267.0977681" /><node x="821.2600784" y="0" z="1256.00418592" /><node x="623.926052913" y="0" z="1042.45379962" /><node x="803.372981027" y="0" z="1028.3541544" /></triangles></road><road id="180" name="外环"><triangles material="road" type="strip"><node x="3145.89775759" y="0" z="462.250374101" /><node x="2969.06450519" y="0" z="48.4509047195" /><node x="2995.30026646" y="0" z="526.608119451" /><node x="2827.15876751" y="0" z="109.094234571" /><node x="2768.05201106" y="0" z="612.622813366" /><node x="2602.59102289" y="0" z="194.094340652" /><node x="2561.35876656" y="0" z="697.85698076" /><node x="2399.69226739" y="0" z="277.763773259" /><node x="2324.80124177" y="0" z="782.496880949" /><node x="2175.98779218" y="0" z="357.804873072" /><node x="1995.05397959" y="0" z="895.61405623" /><node x="1853.34505437" y="0" z="468.484897792" /><node x="1768.95839028" y="0" z="968.094585981" /><node x="1638.18064366" y="0" z="537.46116804" /><node x="1524.07663456" y="0" z="1038.36494583" /><node x="1397.4643994" y="0" z="606.536208186" /><node x="1325.89555176" y="0" z="1097.71325605" /><node x="1200.83348219" y="0" z="665.420297969" /><node x="1116.01292492" y="0" z="1156.31007299" /><node x="994.792109028" y="0" z="722.944681033" /><node x="775.112491086" y="0" z="1251.84774052" /><node x="652.186542854" y="0" z="818.960213505" /><node x="515.952942356" y="0" z="1326.40564764" /><node x="395.636091605" y="0" z="892.767506383" /><node x="283.859653592" y="0" z="1388.43971077" /><node x="169.577380359" y="0" z="953.188643247" /><node x="119.04148154" y="0" z="1430.94018867" /><node x="-1.29844759405" y="0" z="997.251165353" /><node x="64.1188718677" y="0" z="1447.26851784" /><node x="-64.1188718379" y="0" z="1015.92749139" /></triangles></road></block>