<?xml version='1.0' encoding='UTF-8'?>
<block id="14160206365" level="17"><road id="262" name="大学城中八路"><triangles material="road" type="strip"><node x="-66.5056470335" y="0" z="2749.65936702" /><node x="66.5056469738" y="0" z="2870.93589266" /><node x="88.5351797044" y="0" z="2579.6143632" /><node x="219.130014569" y="0" z="2703.54120238" /><node x="503.52355811" y="0" z="2159.39540597" /><node x="630.535636157" y="0" z="2286.95015961" /><node x="921.207674444" y="0" z="1750.41313813" /><node x="1046.18951982" y="0" z="1879.95582745" /><node x="1058.76101007" y="0" z="1619.65183164" /><node x="1189.8861842" y="0" z="1743.35453394" /><node x="1217.49911454" y="0" z="1431.89796289" /><node x="1354.06807971" y="0" z="1549.16180269" /><node x="1596.91363201" y="0" z="996.789287116" /><node x="1731.60156226" y="0" z="1116.21027846" /><node x="2010.83677164" y="0" z="537.648021951" /><node x="2144.07242262" y="0" z="658.679943621" /><node x="2312.06889576" y="0" z="208.555426635" /><node x="2443.53629851" y="0" z="331.51913894" /><node x="2570.81242113" y="0" z="-62.1820610538" /><node x="2700.94145374" y="0" z="62.1820610538" /></triangles></road></block>