<?xml version='1.0' encoding='UTF-8'?>
<block id="14160206468" level="17"><road id="271" name="大学城中四路"><triangles material="road" type="strip"><node x="919.683519289" y="0" z="173.983861413" /><node x="780.352989033" y="0" z="60.0233272798" /><node x="710.600861177" y="0" z="429.612688035" /><node x="573.165647164" y="0" z="313.334900655" /><node x="525.557189405" y="0" z="641.091473132" /><node x="391.871318936" y="0" z="520.528715558" /><node x="294.445418522" y="0" z="889.756581862" /><node x="163.607089803" y="0" z="766.130006831" /><node x="64.9058312625" y="0" z="1128.71250928" /><node x="-64.9058312327" y="0" z="1004.01715138" /></triangles></road><road id="272" name="内环"><triangles material="road" type="strip"><node x="3044.75306144" y="0" z="1007.68443868" /><node x="3070.20920134" y="0" z="829.493572075" /><node x="3027.16487233" y="0" z="1005.17184024" /><node x="3054.42963599" y="0" z="827.239348456" /><node x="2898.02878138" y="0" z="984.040388826" /><node x="2925.75372696" y="0" z="806.183199864" /><node x="2769.80236198" y="0" z="965.043957297" /><node x="2800.85414635" y="0" z="787.679631393" /><node x="2627.29066668" y="0" z="936.221263602" /><node x="2665.24184166" y="0" z="760.252325088" /><node x="2512.72608043" y="0" z="909.96693017" /><node x="2554.80642791" y="0" z="734.944258522" /><node x="2398.98556182" y="0" z="881.333017539" /><node x="2445.1089465" y="0" z="707.328171153" /><node x="2273.82210492" y="0" z="846.477512494" /><node x="2323.39640342" y="0" z="673.433676198" /><node x="2158.6608631" y="0" z="812.559961293" /><node x="2210.43364522" y="0" z="640.163627397" /><node x="2041.77818978" y="0" z="776.779679872" /><node x="2097.62831855" y="0" z="605.63150882" /><node x="1942.96978447" y="0" z="742.515423801" /><node x="2002.68672386" y="0" z="572.708164889" /><node x="1840.84073159" y="0" z="706.097221583" /><node x="1903.25377673" y="0" z="537.251367107" /><node x="1738.73777044" y="0" z="667.010982823" /><node x="1805.35673788" y="0" z="499.775205869" /><node x="1636.97683787" y="0" z="624.875545803" /><node x="1707.11767045" y="0" z="459.098042887" /><node x="1543.84989597" y="0" z="584.626034636" /><node x="1615.86861236" y="0" z="419.660154056" /><node x="1442.57438572" y="0" z="539.968779162" /><node x="1518.70812263" y="0" z="376.81740953" /><node x="1330.73036015" y="0" z="484.845601141" /><node x="1411.80214819" y="0" z="324.127987549" /><node x="1257.84420542" y="0" z="447.22732896" /><node x="1339.37430291" y="0" z="286.74625973" /><node x="1180.80319057" y="0" z="408.706821535" /><node x="1266.41531776" y="0" z="250.266767155" /><node x="1127.64977105" y="0" z="377.766378812" /><node x="1214.88273729" y="0" z="220.269809879" /><node x="1083.3874895" y="0" z="354.470833503" /><node x="1170.08101884" y="0" z="196.690355189" /><node x="805.269371763" y="0" z="195.090325128" /><node x="894.767136559" y="0" z="38.9168635644" /><node x="601.098031655" y="0" z="78.0868508294" /><node x="690.59537743" y="0" z="-78.0868508592" /></triangles></road></block>